gnies/__init__.py
gnies/main.py
gnies/utils.py
gnies/scores/__init__.py
gnies/scores/decomposable_score.py
gnies/scores/gnies_score.py
gnies/scores/interventional.py
gnies/scores/log_likelihood.py
gnies/scores/log_likelihood_means.py
gnies/scores/null_score.py
gnies-0.3.3.dist-info/LICENSE.txt
gnies-0.3.3.dist-info/METADATA
gnies-0.3.3.dist-info/WHEEL
gnies-0.3.3.dist-info/top_level.txt
gnies-0.3.3.dist-info/RECORD
