Metadata-Version: 2.1
Name: gnies
Version: 0.3.3
Home-page: https://github.com/juangamella/gnies
Author: Juan L. Gamella
Author-email: juangamella@gmail.com
License: BSD 3-Clause License
License-File: LICENSE.txt
Requires-Dist: numpy >=1.17.0
Requires-Dist: ges >=1.1.0
